panda_model.libs/libPocoNet-ac8eb170.so.31
panda_model.libs/libPocoFoundation-c26869a6.so.31
panda_model.libs/libpcre-9513aab5.so.1.2.0
panda_model-0.2.0.data/headers/include/pandamodel/model.h
panda_model-0.2.0.data/headers/include/pandamodel/defaults.h
panda_model/_core.cpython-311-x86_64-linux-gnu.so
panda_model/download.py
panda_model/__init__.pyi
panda_model/__init__.py
panda_model/_core/__init__.pyi
panda_model-0.2.0.dist-info/RECORD
panda_model-0.2.0.dist-info/WHEEL
panda_model-0.2.0.dist-info/METADATA
panda_model-0.2.0.dist-info/entry_points.txt
