Metadata-Version: 2.1
Name: panda-model
Version: 0.2.0
Summary: panda-model allows the offline use of the Model class from libfranka in Python and C++.
Keywords: python robotics panda libfranka dynamics franka emika jacobian model control simulation robot-manipulator
Home-page: https://github.com/JeanElsner/panda_model
Author-Email: Jean Elsner <jean.elsner@tum.de>
License:                                  Apache License
Classifier: Intended Audience :: Science/Research
Classifier: Intended Audience :: Developers
Classifier: License :: OSI Approved :: Apache Software License
Classifier: Topic :: Scientific/Engineering
Classifier: Programming Language :: Python :: 3.7
Classifier: Programming Language :: Python :: 3.8
Classifier: Programming Language :: Python :: 3.9
Classifier: Programming Language :: Python :: 3.10
Classifier: Programming Language :: Python :: 3.11
Project-URL: Homepage, https://github.com/JeanElsner/panda_model
Project-URL: Documentation, https://panda-model.readthedocs.io
Project-URL: Repository, https://github.com/JeanElsner/panda_model
Requires-Python: >=3.7
Requires-Dist: numpy
Requires-Dist: pytest; extra == "test"
Provides-Extra: test
